telegrask/__init__.py
telegrask/__main__.py
telegrask/__version__.py
telegrask/app.py
telegrask/cli/__init__.py
telegrask/cli/__main__.py
telegrask/cli/context.py
telegrask/cli/projectinitializer.py
telegrask/cli/templates/.gitignore
telegrask/cli/templates/__init__.py
telegrask/cli/templates/commands.py
telegrask/cli/templates/config.py
telegrask/config.py
telegrask/exceptions.py
telegrask/ext/__init__.py
telegrask/ext/chat.py
telegrask/ext/moderation.py
telegrask/ext/userurl.py
telegrask/helpparser.py
telegrask/inlinequery.py
telegrask-0.3.10.dist-info/entry_points.txt
telegrask-0.3.10.dist-info/LICENSE
telegrask-0.3.10.dist-info/WHEEL
telegrask-0.3.10.dist-info/METADATA
telegrask-0.3.10.dist-info/RECORD
