Metadata-Version: 2.1
Name: telegrask
Version: 0.3.10
Summary: Flask-inspired Telegram bot micro framework for Python.
Home-page: https://github.com/samedamci/telegrask
License: ISC
Keywords: flask-like,framework,library,telegram,bot
Author: samedamci
Author-email: samedamci@disroot.org
Requires-Python: >=3.6.2,<4.0.0
Classifier: Development Status :: 4 - Beta
Classifier: Intended Audience :: Developers
Classifier: License :: OSI Approved
Classifier: License :: OSI Approved :: ISC License (ISCL)
Classifier: Programming Language :: Python
Classifier: Programming Language :: Python :: 3
Classifier: Programming Language :: Python :: 3.6
Classifier: Programming Language :: Python :: 3.7
Classifier: Programming Language :: Python :: 3.8
Classifier: Programming Language :: Python :: 3.9
Classifier: Programming Language :: Python :: Implementation :: CPython
Classifier: Programming Language :: Python :: Implementation :: PyPy
Classifier: Topic :: Software Development :: Libraries
Classifier: Topic :: Software Development :: Libraries :: Application Frameworks
Classifier: Typing :: Typed
Requires-Dist: python-telegram-bot (>=13.7,<14.0)
Project-URL: Documentation, http://telegrask.rtfd.io/
Project-URL: Repository, https://github.com/samedamci/telegrask
